microsoft/teams/ai/__init__.py
microsoft/teams/ai/agent.py
microsoft/teams/ai/ai_model.py
microsoft/teams/ai/chat_prompt.py
microsoft/teams/ai/function.py
microsoft/teams/ai/memory.py
microsoft/teams/ai/message.py
microsoft/teams/ai/plugin.py
microsoft_teams_ai-2.0.0a5.dist-info/METADATA
microsoft_teams_ai-2.0.0a5.dist-info/WHEEL
microsoft_teams_ai-2.0.0a5.dist-info/RECORD
