Metadata-Version: 2.4
Name: microsoft-teams-ai
Version: 2.0.0a5
Summary: package to handle interacting with ai or llms
Author-email: Microsoft <TeamsAISDKFeedback@microsoft.com>
License-Expression: MIT
Keywords: agents,ai,bot,microsoft,teams
Requires-Python: <3.14,>=3.12
Requires-Dist: microsoft-teams-common
